{"canonicalisation":"psp-json-c14n-1","format":"pareto-support-generation-trace","iterations":[{"added_difference":["49","-65","-13"],"added_pool_index":0,"iteration":1,"oracle_adapter":"explicit_enumeration_exact_v1","oracle_decision":{"id":"a014"},"oracle_gap":"-29/3","oracle_outcome":["67","8","32"],"oracle_proof_type":"explicit_enumeration_v1","oracle_trust_level":"P1_FULLY_CHECKABLE","pool_size_after":1,"pool_size_before":0,"restricted_margin":"49/1","restricted_weights":["1/1","0/1","0/1"],"weights":["1/3","1/3","1/3"]},{"added_difference":["-14","-4","48"],"added_pool_index":1,"iteration":2,"oracle_adapter":"explicit_enumeration_exact_v1","oracle_decision":{"id":"a008"},"oracle_gap":"-14/1","oracle_outcome":["4","69","93"],"oracle_proof_type":"explicit_enumeration_v1","oracle_trust_level":"P1_FULLY_CHECKABLE","pool_size_after":2,"pool_size_before":1,"restricted_margin":"35/2","restricted_weights":["61/124","0/1","63/124"],"weights":["1/1","0/1","0/1"]},{"added_difference":["-9","24","-14"],"added_pool_index":2,"iteration":3,"oracle_adapter":"explicit_enumeration_exact_v1","oracle_decision":{"id":"a016"},"oracle_gap":"-1431/124","oracle_outcome":["9","97","31"],"oracle_proof_type":"explicit_enumeration_v1","oracle_trust_level":"P1_FULLY_CHECKABLE","pool_size_after":3,"pool_size_before":2,"restricted_margin":"1006/1395","restricted_weights":["61/124","3601/11160","2069/11160"],"weights":["61/124","0/1","63/124"]},{"iteration":4,"oracle_adapter":"explicit_enumeration_exact_v1","oracle_decision":{"id":"a011"},"oracle_gap":"0/1","oracle_outcome":["18","73","45"],"oracle_proof_type":"explicit_enumeration_v1","oracle_trust_level":"P1_FULLY_CHECKABLE","pool_size_before":3,"termination":"positive_scalar_optimality","weights":["61/124","3601/11160","2069/11160"]}],"result":"positive_weight_supportable","schema_version":"1.0.0"}
