{"candidate":{"decision":{"permutation":[1,3,4,2,0]},"decision_digest":"sha256:49cceb894a1545893bb2f0d80ae1be311f49313bb89374c67f5e790d410091d1","outcome":["120","140","112"]},"canonicalisation":"psp-json-c14n-1","claim":"positive_weight_supportable","format":"pareto-support-certificate","instance_digest":"sha256:f62f015a38a4929edba710e83fb29a3ca6bba1e5ed35f4698c7ddacc3d5a6048","integrity":{"algorithm":"sha256","canonicalisation":"psp-json-c14n-1","certificate_digest":"sha256:3a56bad9ca17df857e2cc348afe1c85a6dbe050279b1c26ec439ac770fdd6845"},"positive_payload":{"candidate_scalar_value":"124/1","oracle":{"adapter":"assignment_exact_hungarian_v1","proof":{"column_potentials":["0/1","0/1","0/1","-31/3","0/1"],"constant_value":"-7/3","matrix_value":"379/3","minimiser_decision":{"permutation":[1,3,4,2,0]},"minimiser_outcome":["120","140","112"],"minimum_value":"124/1","row_potentials":["14/1","64/3","30/1","148/3","22/1"]},"proof_type":"assignment_primal_dual_v1"},"scalar_minimum":"124/1","weight_floor":"1/3","weights":["1/3","1/3","1/3"]},"problem_type":"assignment","provenance":{"algorithm":"exact-exchange-v1","context":{"case_id":"assignment_p3_s2003_epsilon_q42","protocol_sha256":"356a26e2c79b1a6827d24e4236484ef1586c29dc835a59b4bfc202785478ff1a"},"deterministic":true,"exact_arithmetic":"fractions.Fraction","generator":{"name":"pareto-support-proofs","version":"0.6.1"},"oracle_adapter":"assignment_exact_hungarian_v1","trace_digest":"sha256:d0d03b4cba288fffd70da100e0a8fa7c4453f83c82f832ea66324488625e3bbb"},"schema_version":"1.0.0","trust_level":"P1_FULLY_CHECKABLE"}
