{"candidate":{"decision":{"id":"a007"},"decision_digest":"sha256:75eaf302377eab957cc0e9183a7a00b252f7a01efd0c3e226d94852804a67464","outcome":["100","56","119"]},"canonicalisation":"psp-json-c14n-1","claim":"nonnegative_weight_unsupported","format":"pareto-support-certificate","instance_digest":"sha256:ec5daaee674ddcd49a70ff6d0e985e67458e68823d6fb25eff6c05fd4419ebee","integrity":{"algorithm":"sha256","canonicalisation":"psp-json-c14n-1","certificate_digest":"sha256:9d8f945d8a2e1d3e1162e733f2120f109b933f40e927a204e8bd04171ef52e61"},"negative_payload":{"atoms":[{"coefficient":"1","decision":{"id":"a002"},"decision_digest":"sha256:26320e30b550ff7b5c5ab92d79fe6779ee3b3a8d41499f13f240b83e9850032b","outcome":["9","40","1"]}],"coefficient_sum":"1","coordinate_sums":["-91","-16","-118"],"normalisation":"primitive-positive-integers-gcd-1","strict_margin":"16/1"},"problem_type":"explicit_image","provenance":{"algorithm":"exact-exchange-v1","context":{"case_id":"explicit_p3_s1006_hash_control","protocol_sha256":"356a26e2c79b1a6827d24e4236484ef1586c29dc835a59b4bfc202785478ff1a"},"deterministic":true,"exact_arithmetic":"fractions.Fraction","generator":{"name":"pareto-support-proofs","version":"0.6.1"},"oracle_adapter":"explicit_enumeration_exact_v1","trace_digest":"sha256:c223491562c14a958f038902409f6296bb545c6581c4fc9d643447d397d21672"},"schema_version":"1.0.0","trust_level":"P1_FULLY_CHECKABLE"}
