{"candidate":{"decision":{"edge_ids":["e0011"]},"decision_digest":"sha256:fbb1bd10d3b9da63553346e4610bc0ed7a42b1392411ea75ee5f7a8f9d5ef77c","outcome":["6","5","9"]},"canonicalisation":"psp-json-c14n-1","claim":"positive_weight_supportable","format":"pareto-support-certificate","instance_digest":"sha256:835df1a99a756dd6a69c9f4c5090f3a47718dd5754e69f18b5c61205b94c8572","integrity":{"algorithm":"sha256","canonicalisation":"psp-json-c14n-1","certificate_digest":"sha256:bcb7c5390c20998106f0720277a411be6637f71a9e8447a8c1db805fefeca8cf"},"positive_payload":{"candidate_scalar_value":"20/3","oracle":{"adapter":"shortest_path_exact_dijkstra_v1","proof":{"constant_value":"0/1","minimiser_decision":{"edge_ids":["e0011"]},"minimiser_outcome":["6","5","9"],"minimum_value":"20/3","node_potentials":{"v0":"0/1","v1":"70/3","v2":"140/3","v3":"29/3","v4":"46/3","v5":"128/3","v6":"77/3","v7":"20/3"},"path_value":"20/3"},"proof_type":"shortest_path_potentials_v1"},"scalar_minimum":"20/3","weight_floor":"1/3","weights":["1/3","1/3","1/3"]},"problem_type":"shortest_path","provenance":{"algorithm":"exact-exchange-v1","context":{"case_id":"shortest_path_p3_s3004_epsilon_q42","protocol_sha256":"356a26e2c79b1a6827d24e4236484ef1586c29dc835a59b4bfc202785478ff1a"},"deterministic":true,"exact_arithmetic":"fractions.Fraction","generator":{"name":"pareto-support-proofs","version":"0.6.1"},"oracle_adapter":"shortest_path_exact_dijkstra_v1","trace_digest":"sha256:147615c8c25b74b36dfd6e1d2b50240e647fa6c0ae451b89ca96d930b36ff62e"},"schema_version":"1.0.0","trust_level":"P1_FULLY_CHECKABLE"}
